dmp_dash_components/AntdAccordion.py
dmp_dash_components/AntdAccordionItem.py
dmp_dash_components/AntdAffix.py
dmp_dash_components/AntdAlert.py
dmp_dash_components/AntdAnchor.py
dmp_dash_components/AntdAvatar.py
dmp_dash_components/AntdAvatarGroup.py
dmp_dash_components/AntdBackTop.py
dmp_dash_components/AntdBadge.py
dmp_dash_components/AntdBreadcrumb.py
dmp_dash_components/AntdButton.py
dmp_dash_components/AntdCalendar.py
dmp_dash_components/AntdCard.py
dmp_dash_components/AntdCardGrid.py
dmp_dash_components/AntdCarousel.py
dmp_dash_components/AntdCascader.py
dmp_dash_components/AntdCheckCard.py
dmp_dash_components/AntdCheckCardGroup.py
dmp_dash_components/AntdCheckbox.py
dmp_dash_components/AntdCheckboxGroup.py
dmp_dash_components/AntdCol.py
dmp_dash_components/AntdCollapse.py
dmp_dash_components/AntdComment.py
dmp_dash_components/AntdConfigProvider.py
dmp_dash_components/AntdContent.py
dmp_dash_components/AntdCopyText.py
dmp_dash_components/AntdCountdown.py
dmp_dash_components/AntdCustomSkeleton.py
dmp_dash_components/AntdDatePicker.py
dmp_dash_components/AntdDateRangePicker.py
dmp_dash_components/AntdDescriptionItem.py
dmp_dash_components/AntdDescriptions.py
dmp_dash_components/AntdDivider.py
dmp_dash_components/AntdDraggerUpload.py
dmp_dash_components/AntdDrawer.py
dmp_dash_components/AntdDropdown.py
dmp_dash_components/AntdEmpty.py
dmp_dash_components/AntdFooter.py
dmp_dash_components/AntdForm.py
dmp_dash_components/AntdFormItem.py
dmp_dash_components/AntdHeader.py
dmp_dash_components/AntdIcon.py
dmp_dash_components/AntdImage.py
dmp_dash_components/AntdInput.py
dmp_dash_components/AntdInputNumber.py
dmp_dash_components/AntdLayout.py
dmp_dash_components/AntdMentions.py
dmp_dash_components/AntdMenu.py
dmp_dash_components/AntdMessage.py
dmp_dash_components/AntdModal.py
dmp_dash_components/AntdNotification.py
dmp_dash_components/AntdPageHeader.py
dmp_dash_components/AntdPagination.py
dmp_dash_components/AntdParagraph.py
dmp_dash_components/AntdPasteImage.py
dmp_dash_components-1.3.2.dist-info/LICENSE
dmp_dash_components-1.3.2.dist-info/METADATA
dmp_dash_components-1.3.2.dist-info/WHEEL
dmp_dash_components-1.3.2.dist-info/top_level.txt
dmp_dash_components-1.3.2.dist-info/RECORD
