Metadata-Version: 2.1
Name: dmp-dash-components
Version: 1.3.2
Summary: Plotly Dash.
Home-page: https://sicsapps.com
Author: est
Author-email: 123@123.com
License: MIT
Classifier: Framework :: Dash
License-File: LICENSE
Requires-Dist: dash (>=2.6.2)
